[
  {
    "id": "group-gsnwukea9n4",
    "groupname": "Cool Group",
    "adminId": "user-rv4uafl3dt",
    "channels": [
      {
        "id": "channel-pi50inyxall",
        "name": "basketball",
        "banned_users": []
      },
      {
        "id": "channel-4uw1n1y7j4l",
        "name": "tennis",
        "banned_users": []
      },
      {
        "id": "channel-ypugk9l8b5",
        "name": "baseball",
        "banned_users": []
      }
    ],
    "users": [
      "user-rv4uafl3dt"
    ],
    "pendingUsers": [
      "user-rw4uafl3dt"
    ],
    "reported_users": []
  },
  {
    "id": "group-q2xnwe91y3",
    "groupname": "awesome group 2",
    "adminId": "user-rw4uafl3dt",
    "channels": [
      {
        "id": "channel-qstfvu7wuk",
        "name": "baseball",
        "banned_users": []
      },
      {
        "id": "channel-3gmg6uudk4d",
        "name": "tennis",
        "banned_users": []
      }
    ],
    "users": [
      "user-rw4uafl3dt"
    ],
    "pendingUsers": [],
    "reported_users": []
  },
  {
    "id": "group-d7bq7ig4iie",
    "groupname": "Dream Group",
    "adminId": "user-rv4uafl3dt",
    "channels": [],
    "users": [
      "user-rv4uafl3dt"
    ],
    "pendingUsers": [],
    "reported_users": []
  },
  {
    "id": "group-npo01d78jj",
    "groupname": "ill delete this later 2",
    "adminId": "super",
    "channels": [
      {
        "id": "channel-4ku8i9p0vhs",
        "name": "fantastic",
        "banned_users": []
      }
    ],
    "users": [],
    "pendingUsers": [],
    "reported_users": []
  }
]